{
  "experiment_name": "exp_006",
  "window_size": 800,
  "stride": 1,
  "batch_size": 64,
  "lr": 0.0001,
  "weight_decay": 0.0001,
  "beta": 1.75,
  "hidden_channels": 96,
  "num_layers": 2,
  "dropout": 0.3,
  "kernel_size": 7,
  "use_velocity": true,
  "use_acceleration": true,
  "max_rul": 2000,
  "seed": 48,
  "epochs": 200,
  "val_rmse_best": 0.18548194465266915,
  "test_rmse": 9.050093788187926,
  "test_mae": 0.9454487309365663,
  "test_nasa_score": 1374702.232819027,
  "history": [
    {
      "epoch": 1,
      "train_loss": 15917.327473958334,
      "val_rmse": 0.3346164283927685
    },
    {
      "epoch": 2,
      "train_loss": 15670.972981770834,
      "val_rmse": 0.18548194465266915
    },
    {
      "epoch": 3,
      "train_loss": 15770.283854166666,
      "val_rmse": 0.5052427074519441
    },
    {
      "epoch": 4,
      "train_loss": 15695.851236979166,
      "val_rmse": 0.7463579675850434
    },
    {
      "epoch": 5,
      "train_loss": 15743.710069444445,
      "val_rmse": 0.9067317445385998
    },
    {
      "epoch": 6,
      "train_loss": 15809.627170138889,
      "val_rmse": 1.016517407275689
    },
    {
      "epoch": 7,
      "train_loss": 15553.626844618055,
      "val_rmse": 1.1003859992152585
    },
    {
      "epoch": 8,
      "train_loss": 15567.879340277777,
      "val_rmse": 1.16438043863169
    },
    {
      "epoch": 9,
      "train_loss": 15699.001193576389,
      "val_rmse": 1.2209431448242412
    },
    {
      "epoch": 10,
      "train_loss": 15520.497721354166,
      "val_rmse": 1.277254414194257
    },
    {
      "epoch": 11,
      "train_loss": 15420.359483506945,
      "val_rmse": 1.339818857481826
    },
    {
      "epoch": 12,
      "train_loss": 15485.206814236111,
      "val_rmse": 1.4170406212374111
    },
    {
      "epoch": 13,
      "train_loss": 15278.284613715277,
      "val_rmse": 1.492364484045033
    },
    {
      "epoch": 14,
      "train_loss": 15263.273003472223,
      "val_rmse": 1.5616934106708757
    },
    {
      "epoch": 15,
      "train_loss": 14935.105251736111,
      "val_rmse": 1.6284496664184112
    },
    {
      "epoch": 16,
      "train_loss": 15123.295464409723,
      "val_rmse": 1.6895412625607336
    },
    {
      "epoch": 17,
      "train_loss": 14850.972764756945,
      "val_rmse": 1.754322391976225
    },
    {
      "epoch": 18,
      "train_loss": 14938.512044270834,
      "val_rmse": 1.8105701617385386
    },
    {
      "epoch": 19,
      "train_loss": 14840.032986111111,
      "val_rmse": 1.8744960434742883
    },
    {
      "epoch": 20,
      "train_loss": 14724.708658854166,
      "val_rmse": 1.9412377771317433
    },
    {
      "epoch": 21,
      "train_loss": 14680.127387152777,
      "val_rmse": 2.0084303369395284
    },
    {
      "epoch": 22,
      "train_loss": 14444.082139756945,
      "val_rmse": 2.067160475493838
    },
    {
      "epoch": 23,
      "train_loss": 14313.058485243055,
      "val_rmse": 2.127750500203566
    },
    {
      "epoch": 24,
      "train_loss": 14351.123914930555,
      "val_rmse": 2.1871224922668144
    },
    {
      "epoch": 25,
      "train_loss": 14230.531141493055,
      "val_rmse": 2.2378481428167145
    },
    {
      "epoch": 26,
      "train_loss": 14309.686957465277,
      "val_rmse": 2.3073944880893484
    },
    {
      "epoch": 27,
      "train_loss": 13849.869791666666,
      "val_rmse": 2.385611575518648
    },
    {
      "epoch": 28,
      "train_loss": 14085.920572916666,
      "val_rmse": 2.471996132494137
    },
    {
      "epoch": 29,
      "train_loss": 13860.079644097223,
      "val_rmse": 2.554191222116068
    },
    {
      "epoch": 30,
      "train_loss": 13792.453776041666,
      "val_rmse": 2.6336863500896643
    },
    {
      "epoch": 31,
      "train_loss": 13692.704535590277,
      "val_rmse": 2.707723932195637
    },
    {
      "epoch": 32,
      "train_loss": 13715.8017578125,
      "val_rmse": 2.783659161842604
    },
    {
      "epoch": 33,
      "train_loss": 13611.216688368055,
      "val_rmse": 2.8686844066487094
    },
    {
      "epoch": 34,
      "train_loss": 13522.326497395834,
      "val_rmse": 2.961541181948227
    },
    {
      "epoch": 35,
      "train_loss": 13308.117838541666,
      "val_rmse": 3.0536712696873787
    },
    {
      "epoch": 36,
      "train_loss": 13321.683159722223,
      "val_rmse": 3.143643923082575
    },
    {
      "epoch": 37,
      "train_loss": 13314.912543402777,
      "val_rmse": 3.2364540305271907
    },
    {
      "epoch": 38,
      "train_loss": 12943.176974826389,
      "val_rmse": 3.32734265755107
    },
    {
      "epoch": 39,
      "train_loss": 12915.844509548611,
      "val_rmse": 3.4150157012620435
    },
    {
      "epoch": 40,
      "train_loss": 12843.772786458334,
      "val_rmse": 3.4982333054421426
    },
    {
      "epoch": 41,
      "train_loss": 12662.115668402777,
      "val_rmse": 3.5862393409324635
    },
    {
      "epoch": 42,
      "train_loss": 12625.460828993055,
      "val_rmse": 3.6867389509659025
    },
    {
      "epoch": 43,
      "train_loss": 12653.566948784723,
      "val_rmse": 3.7889491584473296
    },
    {
      "epoch": 44,
      "train_loss": 12478.275716145834,
      "val_rmse": 3.89511389839122
    },
    {
      "epoch": 45,
      "train_loss": 12105.279622395834,
      "val_rmse": 3.9978034233590227
    },
    {
      "epoch": 46,
      "train_loss": 12409.166232638889,
      "val_rmse": 4.106569800418771
    },
    {
      "epoch": 47,
      "train_loss": 12185.093858506945,
      "val_rmse": 4.218740995208641
    },
    {
      "epoch": 48,
      "train_loss": 11932.520073784723,
      "val_rmse": 4.327136823270064
    },
    {
      "epoch": 49,
      "train_loss": 12035.500759548611,
      "val_rmse": 4.441686406634785
    },
    {
      "epoch": 50,
      "train_loss": 11725.113932291666,
      "val_rmse": 4.5525807171649
    },
    {
      "epoch": 51,
      "train_loss": 11477.788357204861,
      "val_rmse": 4.662513884659069
    },
    {
      "epoch": 52,
      "train_loss": 11587.130642361111,
      "val_rmse": 4.7812828575572155
    },
    {
      "epoch": 53,
      "train_loss": 11630.231987847223,
      "val_rmse": 4.912681716505764
    },
    {
      "epoch": 54,
      "train_loss": 11308.98828125,
      "val_rmse": 5.042178746396676
    },
    {
      "epoch": 55,
      "train_loss": 11276.598253038195,
      "val_rmse": 5.162288597595713
    },
    {
      "epoch": 56,
      "train_loss": 11204.746419270834,
      "val_rmse": 5.286897653219483
    },
    {
      "epoch": 57,
      "train_loss": 11095.441297743055,
      "val_rmse": 5.406007536708479
    },
    {
      "epoch": 58,
      "train_loss": 11109.472764756945,
      "val_rmse": 5.523565199223267
    },
    {
      "epoch": 59,
      "train_loss": 10826.892795138889,
      "val_rmse": 5.656674476665779
    },
    {
      "epoch": 60,
      "train_loss": 10923.722764756945,
      "val_rmse": 5.795378783494402
    },
    {
      "epoch": 61,
      "train_loss": 10643.112521701389,
      "val_rmse": 5.929412892125496
    },
    {
      "epoch": 62,
      "train_loss": 10481.046332465277,
      "val_rmse": 6.061841552974581
    },
    {
      "epoch": 63,
      "train_loss": 10485.056369357639,
      "val_rmse": 6.193918509716221
    },
    {
      "epoch": 64,
      "train_loss": 10297.970269097223,
      "val_rmse": 6.315539824785908
    },
    {
      "epoch": 65,
      "train_loss": 10376.304470486111,
      "val_rmse": 6.442459619817348
    },
    {
      "epoch": 66,
      "train_loss": 10138.9033203125,
      "val_rmse": 6.582587237261388
    },
    {
      "epoch": 67,
      "train_loss": 10006.9521484375,
      "val_rmse": 6.71092754581142
    },
    {
      "epoch": 68,
      "train_loss": 9897.131076388889,
      "val_rmse": 6.847505719491795
    },
    {
      "epoch": 69,
      "train_loss": 9911.215115017361,
      "val_rmse": 7.001582043454088
    },
    {
      "epoch": 70,
      "train_loss": 9694.473253038195,
      "val_rmse": 7.157061565008162
    },
    {
      "epoch": 71,
      "train_loss": 9476.009494357639,
      "val_rmse": 7.295325285212465
    },
    {
      "epoch": 72,
      "train_loss": 9557.587619357639,
      "val_rmse": 7.434718128956782
    },
    {
      "epoch": 73,
      "train_loss": 9361.644802517361,
      "val_rmse": 7.577699800953147
    },
    {
      "epoch": 74,
      "train_loss": 9335.662489149305,
      "val_rmse": 7.717780069014506
    },
    {
      "epoch": 75,
      "train_loss": 9320.102973090277,
      "val_rmse": 7.858947561852664
    },
    {
      "epoch": 76,
      "train_loss": 9147.658040364584,
      "val_rmse": 8.003608453758513
    },
    {
      "epoch": 77,
      "train_loss": 9158.634223090277,
      "val_rmse": 8.147617326644687
    },
    {
      "epoch": 78,
      "train_loss": 8850.217230902777,
      "val_rmse": 8.293309349935287
    },
    {
      "epoch": 79,
      "train_loss": 8830.275010850695,
      "val_rmse": 8.432611833062959
    },
    {
      "epoch": 80,
      "train_loss": 8762.865559895834,
      "val_rmse": 8.579399353340774
    },
    {
      "epoch": 81,
      "train_loss": 8597.464463975695,
      "val_rmse": 8.733236498859327
    },
    {
      "epoch": 82,
      "train_loss": 8607.690592447916,
      "val_rmse": 8.884277598103619
    },
    {
      "epoch": 83,
      "train_loss": 8514.044650607639,
      "val_rmse": 9.036643985142447
    },
    {
      "epoch": 84,
      "train_loss": 8407.254123263889,
      "val_rmse": 9.185555704391989
    },
    {
      "epoch": 85,
      "train_loss": 8251.29638671875,
      "val_rmse": 9.32725924082729
    },
    {
      "epoch": 86,
      "train_loss": 8249.677680121527,
      "val_rmse": 9.468085716771833
    },
    {
      "epoch": 87,
      "train_loss": 8057.709418402777,
      "val_rmse": 9.615070781906608
    },
    {
      "epoch": 88,
      "train_loss": 8048.464029947917,
      "val_rmse": 9.769276254861541
    },
    {
      "epoch": 89,
      "train_loss": 7930.53076171875,
      "val_rmse": 9.926657730245466
    },
    {
      "epoch": 90,
      "train_loss": 7921.359700520833,
      "val_rmse": 10.075265032881731
    },
    {
      "epoch": 91,
      "train_loss": 7741.632215711806,
      "val_rmse": 10.219694235139569
    },
    {
      "epoch": 92,
      "train_loss": 7663.891981336806,
      "val_rmse": 10.357830156594629
    },
    {
      "epoch": 93,
      "train_loss": 7555.768500434027,
      "val_rmse": 10.493186879908425
    },
    {
      "epoch": 94,
      "train_loss": 7512.020833333333,
      "val_rmse": 10.633571763674045
    },
    {
      "epoch": 95,
      "train_loss": 7584.861436631944,
      "val_rmse": 10.762144506102507
    },
    {
      "epoch": 96,
      "train_loss": 7458.653374565973,
      "val_rmse": 10.681468259014308
    },
    {
      "epoch": 97,
      "train_loss": 7378.936848958333,
      "val_rmse": 10.412761117765601
    },
    {
      "epoch": 98,
      "train_loss": 7294.745985243056,
      "val_rmse": 9.236680455504644
    },
    {
      "epoch": 99,
      "train_loss": 7134.302137586806,
      "val_rmse": 6.634222456431724
    },
    {
      "epoch": 100,
      "train_loss": 7020.417046440973,
      "val_rmse": 5.669714674373114
    },
    {
      "epoch": 101,
      "train_loss": 6908.118760850694,
      "val_rmse": 5.038796621271765
    },
    {
      "epoch": 102,
      "train_loss": 6841.216471354167,
      "val_rmse": 3.4781281495741787
    },
    {
      "epoch": 103,
      "train_loss": 6791.440755208333,
      "val_rmse": 2.945091798696373
    },
    {
      "epoch": 104,
      "train_loss": 6690.106879340277,
      "val_rmse": 2.445348667154178
    },
    {
      "epoch": 105,
      "train_loss": 6627.542697482639,
      "val_rmse": 2.066759328671379
    },
    {
      "epoch": 106,
      "train_loss": 6371.85009765625,
      "val_rmse": 2.1108546531985994
    },
    {
      "epoch": 107,
      "train_loss": 6466.361924913194,
      "val_rmse": 2.153258846604026
    },
    {
      "epoch": 108,
      "train_loss": 6224.476345486111,
      "val_rmse": 2.7227845191439384
    },
    {
      "epoch": 109,
      "train_loss": 6096.913167317708,
      "val_rmse": 2.6377316116614917
    },
    {
      "epoch": 110,
      "train_loss": 6058.348904079861,
      "val_rmse": 2.5516146503260138
    },
    {
      "epoch": 111,
      "train_loss": 5904.911051432292,
      "val_rmse": 2.723703967913081
    },
    {
      "epoch": 112,
      "train_loss": 5965.53466796875,
      "val_rmse": 2.5958846512149045
    },
    {
      "epoch": 113,
      "train_loss": 5739.558322482639,
      "val_rmse": 3.0056217749943546
    },
    {
      "epoch": 114,
      "train_loss": 5673.449896918402,
      "val_rmse": 2.7011387104663385
    },
    {
      "epoch": 115,
      "train_loss": 5645.481228298611,
      "val_rmse": 2.6747453304819957
    },
    {
      "epoch": 116,
      "train_loss": 5489.020697699652,
      "val_rmse": 2.92643452912445
    },
    {
      "epoch": 117,
      "train_loss": 5492.82958984375,
      "val_rmse": 2.7923188120683777
    },
    {
      "epoch": 118,
      "train_loss": 5439.624050564236,
      "val_rmse": 2.842575068512852
    },
    {
      "epoch": 119,
      "train_loss": 5236.902533637152,
      "val_rmse": 2.761506403585331
    },
    {
      "epoch": 120,
      "train_loss": 5197.179389105902,
      "val_rmse": 2.879984591795554
    },
    {
      "epoch": 121,
      "train_loss": 5115.617323133681,
      "val_rmse": 2.8739731713572696
    },
    {
      "epoch": 122,
      "train_loss": 5123.111056857639,
      "val_rmse": 2.933079759324443
    },
    {
      "epoch": 123,
      "train_loss": 5050.383138020833,
      "val_rmse": 2.9195479094517403
    },
    {
      "epoch": 124,
      "train_loss": 4987.218370225694,
      "val_rmse": 2.9386299071417867
    },
    {
      "epoch": 125,
      "train_loss": 4842.658881293402,
      "val_rmse": 3.2207643997749034
    },
    {
      "epoch": 126,
      "train_loss": 4826.614556206598,
      "val_rmse": 2.9266278142578313
    },
    {
      "epoch": 127,
      "train_loss": 4729.125135633681,
      "val_rmse": 2.8964767974846986
    },
    {
      "epoch": 128,
      "train_loss": 4692.493353949652,
      "val_rmse": 3.1926000200228164
    },
    {
      "epoch": 129,
      "train_loss": 4641.020046657986,
      "val_rmse": 2.930166180174537
    },
    {
      "epoch": 130,
      "train_loss": 4634.58203125,
      "val_rmse": 2.988512774176268
    },
    {
      "epoch": 131,
      "train_loss": 4590.838785807292,
      "val_rmse": 2.860001679735635
    },
    {
      "epoch": 132,
      "train_loss": 4456.187961154514,
      "val_rmse": 3.037976404588199
    },
    {
      "epoch": 133,
      "train_loss": 4491.355116102431,
      "val_rmse": 3.367814343195618
    },
    {
      "epoch": 134,
      "train_loss": 4348.889295789931,
      "val_rmse": 2.85893673231969
    },
    {
      "epoch": 135,
      "train_loss": 4327.167100694444,
      "val_rmse": 2.9882645063939948
    },
    {
      "epoch": 136,
      "train_loss": 4313.056179470486,
      "val_rmse": 2.8545001488525052
    },
    {
      "epoch": 137,
      "train_loss": 4217.743272569444,
      "val_rmse": 2.8145527451754773
    },
    {
      "epoch": 138,
      "train_loss": 4151.342909071181,
      "val_rmse": 3.225956242490143
    },
    {
      "epoch": 139,
      "train_loss": 4149.386474609375,
      "val_rmse": 2.8968023198535944
    },
    {
      "epoch": 140,
      "train_loss": 4070.221489800347,
      "val_rmse": 2.867518006810607
    },
    {
      "epoch": 141,
      "train_loss": 4075.3147243923613,
      "val_rmse": 2.854723387607147
    },
    {
      "epoch": 142,
      "train_loss": 3991.764404296875,
      "val_rmse": 2.8628518990585925
    },
    {
      "epoch": 143,
      "train_loss": 3930.124810112847,
      "val_rmse": 2.839754204730409
    },
    {
      "epoch": 144,
      "train_loss": 3968.9828830295137,
      "val_rmse": 2.8016476170748117
    },
    {
      "epoch": 145,
      "train_loss": 3880.595404730903,
      "val_rmse": 2.833178612590584
    },
    {
      "epoch": 146,
      "train_loss": 3878.4345974392363,
      "val_rmse": 2.7205665195725026
    },
    {
      "epoch": 147,
      "train_loss": 3841.7642415364585,
      "val_rmse": 2.7086209552050167
    },
    {
      "epoch": 148,
      "train_loss": 3813.3831651475693,
      "val_rmse": 2.7117201282007817
    },
    {
      "epoch": 149,
      "train_loss": 3787.549560546875,
      "val_rmse": 2.759013710656006
    },
    {
      "epoch": 150,
      "train_loss": 3740.7025282118057,
      "val_rmse": 2.8163267436058224
    },
    {
      "epoch": 151,
      "train_loss": 3754.5127766927085,
      "val_rmse": 2.6986480050301807
    },
    {
      "epoch": 152,
      "train_loss": 3671.1614583333335,
      "val_rmse": 2.7331833042908715
    },
    {
      "epoch": 153,
      "train_loss": 3679.113471137153,
      "val_rmse": 2.7203536324143607
    },
    {
      "epoch": 154,
      "train_loss": 3606.8884548611113,
      "val_rmse": 2.6749215947876057
    },
    {
      "epoch": 155,
      "train_loss": 3576.879937065972,
      "val_rmse": 2.740231377333989
    },
    {
      "epoch": 156,
      "train_loss": 3580.960503472222,
      "val_rmse": 2.6969195383072284
    },
    {
      "epoch": 157,
      "train_loss": 3548.851996527778,
      "val_rmse": 2.794422635649413
    },
    {
      "epoch": 158,
      "train_loss": 3491.322075737847,
      "val_rmse": 2.641633212750464
    },
    {
      "epoch": 159,
      "train_loss": 3442.730482313368,
      "val_rmse": 2.688419626053818
    },
    {
      "epoch": 160,
      "train_loss": 3409.1013454861113,
      "val_rmse": 2.596712385435949
    },
    {
      "epoch": 161,
      "train_loss": 3430.875257703993,
      "val_rmse": 2.6172249314070517
    },
    {
      "epoch": 162,
      "train_loss": 3398.992241753472,
      "val_rmse": 2.639237115180743
    },
    {
      "epoch": 163,
      "train_loss": 3373.5187174479165,
      "val_rmse": 2.629988423726253
    },
    {
      "epoch": 164,
      "train_loss": 3373.5459255642363,
      "val_rmse": 2.591377785859318
    },
    {
      "epoch": 165,
      "train_loss": 3353.2176106770835,
      "val_rmse": 2.538504026826178
    },
    {
      "epoch": 166,
      "train_loss": 3395.4342447916665,
      "val_rmse": 2.6177573405594825
    },
    {
      "epoch": 167,
      "train_loss": 3370.2451171875,
      "val_rmse": 2.600350983783897
    },
    {
      "epoch": 168,
      "train_loss": 3310.2892795138887,
      "val_rmse": 2.57309799874083
    },
    {
      "epoch": 169,
      "train_loss": 3218.155707465278,
      "val_rmse": 2.552850905918651
    },
    {
      "epoch": 170,
      "train_loss": 3240.8601345486113,
      "val_rmse": 2.5548499329006162
    },
    {
      "epoch": 171,
      "train_loss": 3223.346883138021,
      "val_rmse": 2.4917513011908605
    },
    {
      "epoch": 172,
      "train_loss": 3229.7020128038193,
      "val_rmse": 2.661691736841153
    },
    {
      "epoch": 173,
      "train_loss": 3256.0555013020835,
      "val_rmse": 2.656398330324415
    },
    {
      "epoch": 174,
      "train_loss": 3262.2674560546875,
      "val_rmse": 2.6161976346945224
    },
    {
      "epoch": 175,
      "train_loss": 3205.600572374132,
      "val_rmse": 2.550727396709976
    },
    {
      "epoch": 176,
      "train_loss": 3197.299506293403,
      "val_rmse": 2.43907463010017
    },
    {
      "epoch": 177,
      "train_loss": 3165.3122287326387,
      "val_rmse": 2.5431596768977616
    },
    {
      "epoch": 178,
      "train_loss": 3092.297648111979,
      "val_rmse": 2.506411166079456
    },
    {
      "epoch": 179,
      "train_loss": 3088.895941840278,
      "val_rmse": 2.5308407509777684
    },
    {
      "epoch": 180,
      "train_loss": 3225.8786892361113,
      "val_rmse": 2.55071787159998
    },
    {
      "epoch": 181,
      "train_loss": 3170.0836317274307,
      "val_rmse": 2.591124848197269
    },
    {
      "epoch": 182,
      "train_loss": 3138.3032497829863,
      "val_rmse": 2.4811043754391537
    },
    {
      "epoch": 183,
      "train_loss": 3079.9282904730903,
      "val_rmse": 2.4815187710026105
    },
    {
      "epoch": 184,
      "train_loss": 3059.3308783637153,
      "val_rmse": 2.453977122289631
    },
    {
      "epoch": 185,
      "train_loss": 3057.9525282118057,
      "val_rmse": 2.446463027903087
    },
    {
      "epoch": 186,
      "train_loss": 3060.651312934028,
      "val_rmse": 2.455665574692163
    },
    {
      "epoch": 187,
      "train_loss": 3035.964898003472,
      "val_rmse": 2.474824165472258
    },
    {
      "epoch": 188,
      "train_loss": 3055.025933159722,
      "val_rmse": 2.5045654946755236
    },
    {
      "epoch": 189,
      "train_loss": 3056.4341634114585,
      "val_rmse": 2.4708264795340273
    },
    {
      "epoch": 190,
      "train_loss": 3075.3457845052085,
      "val_rmse": 2.423255910807083
    },
    {
      "epoch": 191,
      "train_loss": 3069.7091471354165,
      "val_rmse": 2.445552062962492
    },
    {
      "epoch": 192,
      "train_loss": 3043.987603081597,
      "val_rmse": 2.500163701114586
    },
    {
      "epoch": 193,
      "train_loss": 2995.0796983506943,
      "val_rmse": 2.4097191669126263
    },
    {
      "epoch": 194,
      "train_loss": 3020.6964518229165,
      "val_rmse": 2.5029725053041427
    },
    {
      "epoch": 195,
      "train_loss": 2961.1692165798613,
      "val_rmse": 2.4588249221796508
    },
    {
      "epoch": 196,
      "train_loss": 2972.790296766493,
      "val_rmse": 2.4806258980945803
    },
    {
      "epoch": 197,
      "train_loss": 2941.3731689453125,
      "val_rmse": 2.4948077771254704
    },
    {
      "epoch": 198,
      "train_loss": 2889.4635552300347,
      "val_rmse": 2.480212052861948
    },
    {
      "epoch": 199,
      "train_loss": 2938.148383246528,
      "val_rmse": 2.4521292183757906
    },
    {
      "epoch": 200,
      "train_loss": 2908.5432807074653,
      "val_rmse": 2.4160918680840386
    }
  ]
}